examples/example_1.py
sdc/__init__.py
sdc/api/__init__.py
sdc/api/drone.py
sdc/api/simulation.py
sdc/api/statistics.py
sdc/api/track.py
sdc/core/__init__.py
sdc/core/gradient.py
sdc/core/vector.py
sdc/environment/__init__.py
sdc/environment/reader.py
sdc/environment/track.py
sdc/geometry/__init__.py
sdc/geometry/drone.py
sdc/geometry/ring.py
sdc/tests/__init__.py
sdc/tests/core/__init__.py
sdc/tests/core/test_vector.py
simple_drone_control-1.1.0.dist-info/LICENSE
simple_drone_control-1.1.0.dist-info/METADATA
simple_drone_control-1.1.0.dist-info/WHEEL
simple_drone_control-1.1.0.dist-info/top_level.txt
simple_drone_control-1.1.0.dist-info/RECORD
